[
  {
    "success": true,
    "donor": "Rajendra Sapre",
    "paymentId": 1073,
    "donationId": 5067
  },
  {
    "success": true,
    "donor": "Jaywant Bhopatkar",
    "paymentId": 1074,
    "donationId": 5068
  },
  {
    "success": true,
    "donor": "Subhash Mainkar",
    "paymentId": 1075,
    "donationId": 5069
  },
  {
    "success": true,
    "donor": "Sukhada Athalye",
    "paymentId": 1076,
    "donationId": 5070
  },
  {
    "success": true,
    "donor": "Suniil Karambelkar",
    "paymentId": 1077,
    "donationId": 5071
  },
  {
    "success": true,
    "donor": "Swappna Natekar",
    "paymentId": 1078,
    "donationId": 5072
  },
  {
    "success": true,
    "donor": "Uday Kurane",
    "paymentId": 1079,
    "donationId": 5073
  },
  {
    "success": true,
    "donor": "Uday Tol",
    "paymentId": 1080,
    "donationId": 5074
  },
  {
    "success": true,
    "donor": "Vaishali Varnekar",
    "paymentId": 1081,
    "donationId": 5075
  },
  {
    "success": true,
    "donor": "Vidur Pendharkar",
    "paymentId": 1082,
    "donationId": 5076
  },
  {
    "success": true,
    "donor": "Vijay Laghate",
    "paymentId": 1083,
    "donationId": 5077
  },
  {
    "success": true,
    "donor": "Vivek Moghe",
    "paymentId": 1084,
    "donationId": 5078
  },
  {
    "success": true,
    "donor": "Vivek Nanivadekar",
    "paymentId": 1085,
    "donationId": 5079
  }
]